flytekitplugins_k8sdataservice-1.16.12-py3.14-nspkg.pth
flytekitplugins/k8sdataservice/__init__.py
flytekitplugins/k8sdataservice/connector.py
flytekitplugins/k8sdataservice/sensor.py
flytekitplugins/k8sdataservice/task.py
flytekitplugins/k8sdataservice/k8s/__init__.py
flytekitplugins/k8sdataservice/k8s/kube_config.py
flytekitplugins/k8sdataservice/k8s/manager.py
tests/k8sdataservice/connector.py
tests/k8sdataservice/test_sensor.py
tests/k8sdataservice/test_task.py
tests/k8sdataservice/k8s/test_kube_config.py
tests/k8sdataservice/k8s/test_manager.py
tests/k8sdataservice/utils/test_resources.py
utils/__init__.py
utils/infra.py
utils/resources.py
flytekitplugins_k8sdataservice-1.16.12.dist-info/METADATA
flytekitplugins_k8sdataservice-1.16.12.dist-info/WHEEL
flytekitplugins_k8sdataservice-1.16.12.dist-info/entry_points.txt
flytekitplugins_k8sdataservice-1.16.12.dist-info/namespace_packages.txt
flytekitplugins_k8sdataservice-1.16.12.dist-info/top_level.txt
flytekitplugins_k8sdataservice-1.16.12.dist-info/RECORD
