Metadata-Version: 2.4
Name: flytekitplugins-k8sdataservice
Version: 1.16.12
Summary: Flytekit K8s Data Service Plugin
Author: LinkedIn
Author-email: shuliang@linkedin.com
License: apache2
Classifier: Intended Audience :: Science/Research
Classifier: Intended Audience :: Developers
Classifier: License :: OSI Approved :: Apache Software License
Classifier: Programming Language :: Python :: 3.9
Classifier: Programming Language :: Python :: 3.10
Classifier: Programming Language :: Python :: 3.11
Classifier: Programming Language :: Python :: 3.12
Classifier: Topic :: Scientific/Engineering
Classifier: Topic :: Scientific/Engineering :: Artificial Intelligence
Classifier: Topic :: Software Development
Classifier: Topic :: Software Development :: Libraries
Classifier: Topic :: Software Development :: Libraries :: Python Modules
Requires-Python: >=3.9
Requires-Dist: flytekit<2.0.0,>=1.11.0
Requires-Dist: kubernetes<24.0.0,>=23.6.0
Requires-Dist: flyteidl<2.0.0,>=1.11.0
Dynamic: author
Dynamic: author-email
Dynamic: classifier
Dynamic: license
Dynamic: requires-dist
Dynamic: requires-python
Dynamic: summary
